sthlmkollektivtrafik/__init__.py
sthlmkollektivtrafik/platsuppslag.py
sthlmkollektivtrafik/realtidsinformation.py
sthlmkollektivtrafik/reseplanerare.py
sthlmkollektivtrafik/storningsinformation.py
sthlmkollektivtrafik-0.1.4.dist-info/LICENSE
sthlmkollektivtrafik-0.1.4.dist-info/METADATA
sthlmkollektivtrafik-0.1.4.dist-info/WHEEL
sthlmkollektivtrafik-0.1.4.dist-info/top_level.txt
sthlmkollektivtrafik-0.1.4.dist-info/RECORD
