Metadata-Version: 2.1
Name: sthlmkollektivtrafik
Version: 0.1.4
Summary: Python library for easier use of www.trafiklab.se api's'
Home-page: https://github.com/WIGRU/sthlmkollektivtrafik
Author: William Grunder
Author-email: William.grunder@gmail.com
License: UNKNOWN
Platform: UNKNOWN
Classifier: Programming Language :: Python :: 3
Classifier: License :: OSI Approved :: MIT License
Classifier: Operating System :: OS Independent
Requires-Python: >=3.6
Requires-Dist: requests
